uma/__init__.py
uma/__pycache__/__init__.cpython-37.pyc
uma/__pycache__/converter.cpython-37.pyc
uma-1.0.dist-info/LICENSE
uma-1.0.dist-info/METADATA
uma-1.0.dist-info/WHEEL
uma-1.0.dist-info/top_level.txt
uma-1.0.dist-info/RECORD
