Metadata-Version: 2.1
Name: uma
Version: 1.0
Summary: A python package to collect pyomo results as pandas dataframe for easier access.
Home-page: https://github.com/dgusain1/uma
Author: Digvijay Gusain
Author-email: digvijay.gusain29@gmail.com
License: MIT
Platform: UNKNOWN
Classifier: License :: OSI Approved :: MIT License
Classifier: Programming Language :: Python :: 3.6
Classifier: Programming Language :: Python :: 3.7
Classifier: Programming Language :: Python :: 3.8
Requires-Dist: numpy
Requires-Dist: pandas
Requires-Dist: pyomo
